setup.py
listprint/__init__.py
listprint/stack.py
printlistoop.egg-info/PKG-INFO
printlistoop.egg-info/SOURCES.txt
printlistoop.egg-info/dependency_links.txt
printlistoop.egg-info/not-zip-safe
printlistoop.egg-info/top_level.txt