Metadata-Version: 1.0
Name: printlistoop
Version: 0.1
Summary: The funniest joke in the world- Nishant
Home-page: http://github.com/nawarkhede
Author: Nishant
Author-email: nishant.nawarkhede@gmail.com
License: MIT
Platform: UNKNOWN
